tests/__init__.py
tests/test_core.py
tests/test_parser.py
tests/test_venv_manager.py
treefile/__init__.py
treefile/cli.py
treefile/context_menu.py
treefile/core.py
treefile/parser.py
treefile/utils.py
treefile/venv_manager.py
treefile/icons/treefile.icns
treefile/icons/treefile.ico
treefile/icons/treefile.png
treefile-1.0.0.dist-info/LICENSE
treefile-1.0.0.dist-info/METADATA
treefile-1.0.0.dist-info/WHEEL
treefile-1.0.0.dist-info/entry_points.txt
treefile-1.0.0.dist-info/top_level.txt
treefile-1.0.0.dist-info/RECORD
