Metadata-Version: 2.2
Name: treefile
Version: 1.0.0
Summary: Generate file trees from .treefile configurations with integrated file icon support
Home-page: https://github.com/BenevolenceMessiah/treefile
Author: Benevolence Messiah
Author-email: benevolence.messiah@gmail.com
Classifier: Programming Language :: Python :: 3
Classifier: License :: OSI Approved :: MIT License
Classifier: Operating System :: OS Independent
Requires-Python: >=3.6
License-File: LICENSE
Requires-Dist: click
Requires-Dist: PyYAML
Dynamic: author
Dynamic: author-email
Dynamic: classifier
Dynamic: description
Dynamic: description-content-type
Dynamic: home-page
Dynamic: requires-dist
Dynamic: requires-python
Dynamic: summary
